SphinxZhongwenWendang/README.md
SphinxZhongwenWendang/__init__.py
SphinxZhongwenWendang/__main__.py
SphinxZhongwenWendang/file.epub
SphinxZhongwenWendang/index.html
SphinxZhongwenWendang/css/__init__.py
SphinxZhongwenWendang/css/annotations.css
SphinxZhongwenWendang/css/main.css
SphinxZhongwenWendang/css/normalize.css
SphinxZhongwenWendang/css/popup.css
SphinxZhongwenWendang/font/__init__.py
SphinxZhongwenWendang/font/fontello.eot
SphinxZhongwenWendang/font/fontello.svg
SphinxZhongwenWendang/font/fontello.ttf
SphinxZhongwenWendang/font/fontello.woff
SphinxZhongwenWendang/img/__init__.py
SphinxZhongwenWendang/img/annotator-glyph-sprite.png
SphinxZhongwenWendang/img/annotator-icon-sprite.png
SphinxZhongwenWendang/img/apple-touch-icon.png
SphinxZhongwenWendang/img/cancelfullscreen.png
SphinxZhongwenWendang/img/close.png
SphinxZhongwenWendang/img/fullscreen.png
SphinxZhongwenWendang/img/loader.gif
SphinxZhongwenWendang/img/menu-icon.png
SphinxZhongwenWendang/img/save.png
SphinxZhongwenWendang/img/saved.png
SphinxZhongwenWendang/img/settings-s.png
SphinxZhongwenWendang/img/settings.png
SphinxZhongwenWendang/img/star.png
SphinxZhongwenWendang/js/__init__.py
SphinxZhongwenWendang/js/epub.js
SphinxZhongwenWendang/js/epub.min.js
SphinxZhongwenWendang/js/epub.min.map
SphinxZhongwenWendang/js/hooks.min.js
SphinxZhongwenWendang/js/hooks.min.map
SphinxZhongwenWendang/js/reader.js
SphinxZhongwenWendang/js/reader.js.map
SphinxZhongwenWendang/js/reader.min.js
SphinxZhongwenWendang/js/reader.min.map
SphinxZhongwenWendang/js/hooks/__init__.py
SphinxZhongwenWendang/js/hooks/extensions/__init__.py
SphinxZhongwenWendang/js/hooks/extensions/highlight.js
SphinxZhongwenWendang/js/libs/__init__.py
SphinxZhongwenWendang/js/libs/jquery.min.js
SphinxZhongwenWendang/js/libs/localforage.min.js
SphinxZhongwenWendang/js/libs/screenfull.js
SphinxZhongwenWendang/js/libs/screenfull.min.js
SphinxZhongwenWendang/js/libs/zip.min.js
SphinxZhongwenWendang/js/plugins/__init__.py
sphinx_zhongwen_wendang-2024.3.2.0.dist-info/METADATA
sphinx_zhongwen_wendang-2024.3.2.0.dist-info/WHEEL
sphinx_zhongwen_wendang-2024.3.2.0.dist-info/entry_points.txt
sphinx_zhongwen_wendang-2024.3.2.0.dist-info/top_level.txt
sphinx_zhongwen_wendang-2024.3.2.0.dist-info/RECORD
